IterPipe/IterPipe.py
IterPipe/__init__.py
IterPipe-0.0.3.dist-info/LICENSE
IterPipe-0.0.3.dist-info/METADATA
IterPipe-0.0.3.dist-info/WHEEL
IterPipe-0.0.3.dist-info/top_level.txt
IterPipe-0.0.3.dist-info/RECORD
