Metadata-Version: 2.1
Name: IterPipe
Version: 0.0.3
Summary: Iterator pipeline wrapper in the spirit of Martin Fowler's Collection Pipeline pattern
Home-page: https://github.com/ZianVW/IterPipe.git
Author: Zian van Wijk
Author-email: zian@cognizon.com
License: UNKNOWN
Platform: UNKNOWN
Classifier: Programming Language :: Python :: 3
Classifier: License :: OSI Approved :: GNU General Public License v3 (GPLv3)
Classifier: Operating System :: OS Independent
